<?xml version="1.0" encoding="utf-8"?>
<TextureAtlas imagePath="Sonic.png">
	<!-- Created with Adobe Animate version 19.0.0.326 -->
	<!-- http://www.adobe.com/products/animate.html -->
	<SubTexture name="Sonic DOWN0000" x="0" y="0" width="720" height="423" frameX="0" frameY="-12" frameWidth="720" frameHeight="435"/>
	<SubTexture name="Sonic DOWN0001" x="721" y="0" width="720" height="423" frameX="0" frameY="-12" frameWidth="720" frameHeight="435"/>
	<SubTexture name="Sonic DOWN0002" x="1442" y="0" width="709" height="435" frameX="-10" frameY="0" frameWidth="720" frameHeight="435"/>
	<SubTexture name="Sonic DOWN0003" x="2152" y="0" width="709" height="435" frameX="-10" frameY="0" frameWidth="720" frameHeight="435"/>
	<SubTexture name="Sonic DOWN0004" x="2862" y="0" width="701" height="431" frameX="-10" frameY="-4" frameWidth="720" frameHeight="435"/>
	<SubTexture name="Sonic DOWN0005" x="0" y="436" width="701" height="431" frameX="-10" frameY="-4" frameWidth="720" frameHeight="435"/>
	<SubTexture name="Sonic DOWN0006" x="702" y="436" width="701" height="431" frameX="-10" frameY="-4" frameWidth="720" frameHeight="435"/>
	<SubTexture name="Sonic DOWN0007" x="702" y="436" width="701" height="431" frameX="-10" frameY="-4" frameWidth="720" frameHeight="435"/>
	<SubTexture name="Sonic DOWN0008" x="1404" y="436" width="701" height="431" frameX="-10" frameY="-4" frameWidth="720" frameHeight="435"/>
	<SubTexture name="Sonic DOWN0009" x="1404" y="436" width="701" height="431" frameX="-10" frameY="-4" frameWidth="720" frameHeight="435"/>
	<SubTexture name="Sonic DOWN0010" x="2106" y="436" width="701" height="431" frameX="-10" frameY="-4" frameWidth="720" frameHeight="435"/>
	<SubTexture name="Sonic DOWN0011" x="2106" y="436" width="701" height="431" frameX="-10" frameY="-4" frameWidth="720" frameHeight="435"/>
	<SubTexture name="Sonic DOWN0012" x="2808" y="436" width="701" height="431" frameX="-10" frameY="-4" frameWidth="720" frameHeight="435"/>
	<SubTexture name="Sonic DOWN0013" x="2808" y="436" width="701" height="431" frameX="-10" frameY="-4" frameWidth="720" frameHeight="435"/>
	<SubTexture name="Sonic DOWN0014" x="0" y="868" width="701" height="431" frameX="-10" frameY="-4" frameWidth="720" frameHeight="435"/>
	<SubTexture name="Sonic IDLE0000" x="702" y="868" width="512" height="558" frameX="-41" frameY="-23" frameWidth="553" frameHeight="581"/>
	<SubTexture name="Sonic IDLE0001" x="1215" y="868" width="512" height="558" frameX="-41" frameY="-23" frameWidth="553" frameHeight="581"/>
	<SubTexture name="Sonic IDLE0002" x="1728" y="868" width="501" height="571" frameX="-27" frameY="-10" frameWidth="553" frameHeight="581"/>
	<SubTexture name="Sonic IDLE0003" x="1728" y="868" width="501" height="571" frameX="-27" frameY="-10" frameWidth="553" frameHeight="581"/>
	<SubTexture name="Sonic IDLE0004" x="2230" y="868" width="507" height="576" frameX="-15" frameY="-5" frameWidth="553" frameHeight="581"/>
	<SubTexture name="Sonic IDLE0005" x="2738" y="868" width="507" height="576" frameX="-15" frameY="-5" frameWidth="553" frameHeight="581"/>
	<SubTexture name="Sonic IDLE0006" x="3246" y="868" width="514" height="580" frameX="-8" frameY="-1" frameWidth="553" frameHeight="581"/>
	<SubTexture name="Sonic IDLE0007" x="0" y="1449" width="514" height="580" frameX="-8" frameY="-1" frameWidth="553" frameHeight="581"/>
	<SubTexture name="Sonic IDLE0008" x="515" y="1449" width="522" height="581" frameX="0" frameY="0" frameWidth="553" frameHeight="581"/>
	<SubTexture name="Sonic IDLE0009" x="1038" y="1449" width="522" height="581" frameX="0" frameY="0" frameWidth="553" frameHeight="581"/>
	<SubTexture name="Sonic IDLE0010" x="1561" y="1449" width="522" height="581" frameX="0" frameY="0" frameWidth="553" frameHeight="581"/>
	<SubTexture name="Sonic IDLE0011" x="2084" y="1449" width="525" height="581" frameX="0" frameY="0" frameWidth="553" frameHeight="581"/>
	<SubTexture name="Sonic IDLE0012" x="2610" y="1449" width="525" height="581" frameX="0" frameY="0" frameWidth="553" frameHeight="581"/>
	<SubTexture name="Sonic IDLE0013" x="3136" y="1449" width="512" height="581" frameX="0" frameY="0" frameWidth="553" frameHeight="581"/>
	<SubTexture name="Sonic IDLE0014" x="3136" y="1449" width="512" height="581" frameX="0" frameY="0" frameWidth="553" frameHeight="581"/>
	<SubTexture name="Sonic LEFT0000" x="0" y="2031" width="613" height="520" frameX="0" frameY="-8" frameWidth="638" frameHeight="528"/>
	<SubTexture name="Sonic LEFT0001" x="614" y="2031" width="613" height="520" frameX="0" frameY="-8" frameWidth="638" frameHeight="528"/>
	<SubTexture name="Sonic LEFT0002" x="1228" y="2031" width="619" height="528" frameX="-16" frameY="0" frameWidth="638" frameHeight="528"/>
	<SubTexture name="Sonic LEFT0003" x="1228" y="2031" width="619" height="528" frameX="-16" frameY="0" frameWidth="638" frameHeight="528"/>
	<SubTexture name="Sonic LEFT0004" x="1848" y="2031" width="610" height="520" frameX="-28" frameY="-8" frameWidth="638" frameHeight="528"/>
	<SubTexture name="Sonic LEFT0005" x="2459" y="2031" width="610" height="520" frameX="-28" frameY="-8" frameWidth="638" frameHeight="528"/>
	<SubTexture name="Sonic LEFT0006" x="3070" y="2031" width="610" height="520" frameX="-28" frameY="-8" frameWidth="638" frameHeight="528"/>
	<SubTexture name="Sonic LEFT0007" x="0" y="2560" width="610" height="520" frameX="-28" frameY="-8" frameWidth="638" frameHeight="528"/>
	<SubTexture name="Sonic LEFT0008" x="611" y="2560" width="610" height="520" frameX="-28" frameY="-8" frameWidth="638" frameHeight="528"/>
	<SubTexture name="Sonic LEFT0009" x="1222" y="2560" width="610" height="520" frameX="-28" frameY="-8" frameWidth="638" frameHeight="528"/>
	<SubTexture name="Sonic LEFT0010" x="1833" y="2560" width="610" height="520" frameX="-28" frameY="-8" frameWidth="638" frameHeight="528"/>
	<SubTexture name="Sonic LEFT0011" x="2444" y="2560" width="610" height="520" frameX="-28" frameY="-8" frameWidth="638" frameHeight="528"/>
	<SubTexture name="Sonic LEFT0012" x="3055" y="2560" width="610" height="520" frameX="-28" frameY="-8" frameWidth="638" frameHeight="528"/>
	<SubTexture name="Sonic LEFT0013" x="0" y="3081" width="610" height="520" frameX="-28" frameY="-8" frameWidth="638" frameHeight="528"/>
	<SubTexture name="Sonic LEFT0014" x="0" y="3081" width="610" height="520" frameX="-28" frameY="-8" frameWidth="638" frameHeight="528"/>
	<SubTexture name="Sonic POSE0000" x="611" y="3081" width="527" height="577" frameX="0" frameY="0" frameWidth="530" frameHeight="577"/>
	<SubTexture name="Sonic POSE0001" x="1139" y="3081" width="527" height="577" frameX="0" frameY="0" frameWidth="530" frameHeight="577"/>
	<SubTexture name="Sonic POSE0002" x="1667" y="3081" width="513" height="576" frameX="-17" frameY="-1" frameWidth="530" frameHeight="577"/>
	<SubTexture name="Sonic POSE0003" x="2181" y="3081" width="513" height="576" frameX="-17" frameY="-1" frameWidth="530" frameHeight="577"/>
	<SubTexture name="Sonic POSE0004" x="2695" y="3081" width="503" height="575" frameX="-27" frameY="-2" frameWidth="530" frameHeight="577"/>
	<SubTexture name="Sonic POSE0005" x="3199" y="3081" width="503" height="576" frameX="-27" frameY="-1" frameWidth="530" frameHeight="577"/>
	<SubTexture name="Sonic POSE0006" x="0" y="3659" width="513" height="576" frameX="-17" frameY="-1" frameWidth="530" frameHeight="577"/>
	<SubTexture name="Sonic POSE0007" x="514" y="3659" width="513" height="576" frameX="-17" frameY="-1" frameWidth="530" frameHeight="577"/>
	<SubTexture name="Sonic POSE0008" x="1028" y="3659" width="513" height="576" frameX="-17" frameY="-1" frameWidth="530" frameHeight="577"/>
	<SubTexture name="Sonic POSE0009" x="1542" y="3659" width="513" height="576" frameX="-17" frameY="-1" frameWidth="530" frameHeight="577"/>
	<SubTexture name="Sonic POSE0010" x="1542" y="3659" width="513" height="576" frameX="-17" frameY="-1" frameWidth="530" frameHeight="577"/>
	<SubTexture name="Sonic POSE0011" x="2056" y="3659" width="513" height="576" frameX="-17" frameY="-1" frameWidth="530" frameHeight="577"/>
	<SubTexture name="Sonic POSE0012" x="2056" y="3659" width="513" height="576" frameX="-17" frameY="-1" frameWidth="530" frameHeight="577"/>
	<SubTexture name="Sonic POSE0013" x="2570" y="3659" width="513" height="576" frameX="-17" frameY="-1" frameWidth="530" frameHeight="577"/>
	<SubTexture name="Sonic POSE0014" x="3084" y="3659" width="513" height="576" frameX="-17" frameY="-1" frameWidth="530" frameHeight="577"/>
	<SubTexture name="Sonic RIGHT0000" x="0" y="4236" width="563" height="497" frameX="-2" frameY="0" frameWidth="565" frameHeight="497"/>
	<SubTexture name="Sonic RIGHT0001" x="0" y="4236" width="563" height="497" frameX="-2" frameY="0" frameWidth="565" frameHeight="497"/>
	<SubTexture name="Sonic RIGHT0002" x="564" y="4236" width="564" height="495" frameX="-1" frameY="-2" frameWidth="565" frameHeight="497"/>
	<SubTexture name="Sonic RIGHT0003" x="1129" y="4236" width="564" height="495" frameX="-1" frameY="-2" frameWidth="565" frameHeight="497"/>
	<SubTexture name="Sonic RIGHT0004" x="1694" y="4236" width="565" height="482" frameX="0" frameY="-15" frameWidth="565" frameHeight="497"/>
	<SubTexture name="Sonic RIGHT0005" x="2260" y="4236" width="565" height="482" frameX="0" frameY="-15" frameWidth="565" frameHeight="497"/>
	<SubTexture name="Sonic RIGHT0006" x="2826" y="4236" width="565" height="482" frameX="0" frameY="-15" frameWidth="565" frameHeight="497"/>
	<SubTexture name="Sonic RIGHT0007" x="3392" y="4236" width="565" height="482" frameX="0" frameY="-15" frameWidth="565" frameHeight="497"/>
	<SubTexture name="Sonic RIGHT0008" x="0" y="4734" width="565" height="482" frameX="0" frameY="-15" frameWidth="565" frameHeight="497"/>
	<SubTexture name="Sonic RIGHT0009" x="0" y="4734" width="565" height="482" frameX="0" frameY="-15" frameWidth="565" frameHeight="497"/>
	<SubTexture name="Sonic RIGHT0010" x="0" y="4734" width="565" height="482" frameX="0" frameY="-15" frameWidth="565" frameHeight="497"/>
	<SubTexture name="Sonic RIGHT0011" x="0" y="4734" width="565" height="482" frameX="0" frameY="-15" frameWidth="565" frameHeight="497"/>
	<SubTexture name="Sonic RIGHT0012" x="0" y="4734" width="565" height="482" frameX="0" frameY="-15" frameWidth="565" frameHeight="497"/>
	<SubTexture name="Sonic RIGHT0013" x="0" y="4734" width="565" height="482" frameX="0" frameY="-15" frameWidth="565" frameHeight="497"/>
	<SubTexture name="Sonic RIGHT0014" x="0" y="4734" width="565" height="482" frameX="0" frameY="-15" frameWidth="565" frameHeight="497"/>
	<SubTexture name="Sonic UP0000" x="566" y="4734" width="534" height="685" frameX="-13" frameY="0" frameWidth="547" frameHeight="685"/>
	<SubTexture name="Sonic UP0001" x="1101" y="4734" width="534" height="685" frameX="-13" frameY="0" frameWidth="547" frameHeight="685"/>
	<SubTexture name="Sonic UP0002" x="1636" y="4734" width="531" height="672" frameX="-7" frameY="-13" frameWidth="547" frameHeight="685"/>
	<SubTexture name="Sonic UP0003" x="2168" y="4734" width="531" height="672" frameX="-7" frameY="-13" frameWidth="547" frameHeight="685"/>
	<SubTexture name="Sonic UP0004" x="2700" y="4734" width="539" height="665" frameX="0" frameY="-19" frameWidth="547" frameHeight="685"/>
	<SubTexture name="Sonic UP0005" x="3240" y="4734" width="539" height="665" frameX="0" frameY="-19" frameWidth="547" frameHeight="685"/>
	<SubTexture name="Sonic UP0006" x="0" y="5420" width="539" height="665" frameX="0" frameY="-19" frameWidth="547" frameHeight="685"/>
	<SubTexture name="Sonic UP0007" x="0" y="5420" width="539" height="665" frameX="0" frameY="-19" frameWidth="547" frameHeight="685"/>
	<SubTexture name="Sonic UP0008" x="540" y="5420" width="539" height="665" frameX="0" frameY="-19" frameWidth="547" frameHeight="685"/>
	<SubTexture name="Sonic UP0009" x="540" y="5420" width="539" height="665" frameX="0" frameY="-19" frameWidth="547" frameHeight="685"/>
	<SubTexture name="Sonic UP0010" x="1080" y="5420" width="539" height="665" frameX="0" frameY="-19" frameWidth="547" frameHeight="685"/>
	<SubTexture name="Sonic UP0011" x="1080" y="5420" width="539" height="665" frameX="0" frameY="-19" frameWidth="547" frameHeight="685"/>
	<SubTexture name="Sonic UP0012" x="1620" y="5420" width="539" height="665" frameX="0" frameY="-19" frameWidth="547" frameHeight="685"/>
	<SubTexture name="Sonic UP0013" x="2160" y="5420" width="539" height="665" frameX="0" frameY="-19" frameWidth="547" frameHeight="685"/>
	<SubTexture name="Sonic UP0014" x="2160" y="5420" width="539" height="665" frameX="0" frameY="-19" frameWidth="547" frameHeight="685"/>
</TextureAtlas>
